tias/__init__.py
tias/__main__.py
tias/aliases.py
tias/app.py
tias/errors.py
tias/jargon.py
tias/main.py
tias/multiline_input.py
tias-0.5.1.dist-info/LICENSE
tias-0.5.1.dist-info/METADATA
tias-0.5.1.dist-info/WHEEL
tias-0.5.1.dist-info/entry_points.txt
tias-0.5.1.dist-info/top_level.txt
tias-0.5.1.dist-info/RECORD
