Metadata-Version: 2.1
Name: tias
Version: 0.5.1
Summary: Quickly run code in almost any language
Home-page: https://github.com/wheelercj/tias
Author: Chris Wheeler
Author-email: christopher.wheeler.320@my.csun.edu
License: MIT
Keywords: code,development,programming
Platform: unix
Platform: linux
Platform: osx
Platform: cygwin
Platform: win32
Classifier: Programming Language :: Python :: 3 :: Only
Classifier: Programming Language :: Python :: 3
Classifier: Programming Language :: Python :: 3.9
Classifier: Programming Language :: Python :: 3.10
Classifier: Programming Language :: Python :: 3.11
Requires-Python: >=3.9
License-File: LICENSE
Requires-Dist: aiodns (>=3.0.0)
Requires-Dist: aiohttp (>=3.8.3)
Requires-Dist: aiosignal (>=1.2.0)
Requires-Dist: async-timeout (>=4.0.2)
Requires-Dist: async-tio (>=1.3.2)
Requires-Dist: attrs (>=21.4.0)
Requires-Dist: cffi (>=1.15.1)
Requires-Dist: charset-normalizer (>=2.1.0)
Requires-Dist: click (>=8.1.3)
Requires-Dist: colorama (>=0.4.5)
Requires-Dist: frozenlist (>=1.3.1)
Requires-Dist: idna (>=3.3)
Requires-Dist: keyboard (>=0.13.5)
Requires-Dist: multidict (>=6.0.2)
Requires-Dist: mypy-extensions (>=0.4.3)
Requires-Dist: packaging (>=21.3)
Requires-Dist: pathspec (>=0.9.0)
Requires-Dist: platformdirs (>=2.5.2)
Requires-Dist: pycares (>=4.2.1)
Requires-Dist: pycparser (>=2.21)
Requires-Dist: pyparsing (>=3.0.9)
Requires-Dist: python-dateutil (>=2.8.2)
Requires-Dist: tomli (>=2.0.1)
Requires-Dist: typing-extensions (>=4.3.0)
Requires-Dist: yarl (>=1.8.1)
